{
    "id": "arphic-1999",
    "name": "Arphic Public License",
    "creator": [],
    "since": "",
    "description": "",
    "permissions": [],
    "conditions": [],
    "limitations": [],
    "body": "ARPHIC PUBLIC LICENSE\n\nCopyright (C) 1999 Arphic Technology Co., Ltd.\n11Fl. No.168, Yung Chi Rd., Taipei, 110 Taiwan\nAll rights reserved except as specified below.\n\nEveryone is permitted to copy and distribute verbatim copies\nof this license document, but changing it is forbidden.\n\nPreamble\n\nThe licenses for most software are designed to take away\nyour freedom to share and change it. By contrast, the\nARPHIC PUBLIC LICENSE specifically permits and encourages\nyou to use this software, provided that you give the\nrecipients all the rights that we gave you and make\nsure they can get the modifications of this software.\n\nLegal Terms\n\n0. \n\n1. \n\n2. \n\n3. \n\n4. \n\n5. \n\n6. \n\n7. \n\n8. ",
    "type": "source-available"
}