{"id":"cdla-sharing-1.0","name":"Community Data License Agreement Sharing 1.0","creator":[],"since":"","description":"","permissions":[],"conditions":[],"limitations":[],"body":"This is the Community Data License Agreement - Sharing, Version 1.0 (\"Agreement\"). Data is provided to You under this Agreement by each of the Data Providers. Your exercise of any of the rights and permissions granted below constitutes Your acceptance and agreement to be bound by the terms and conditions of this Agreement.\n\nThe benefits that each Data Provider receives from making Data available and that You receive from Data or otherwise under these terms and conditions shall be deemed sufficient consideration for the formation of this Agreement. Accordingly, Data Provider(s) and You (the \"Parties\") agree as follows:","type":"source-available"}