{
    "id": "cecill-1.1",
    "name": "CeCILL Free Software License Agreement v1.1",
    "creator": [],
    "since": "",
    "description": "",
    "permissions": [],
    "conditions": [],
    "limitations": [],
    "body": "FREE SOFTWARE LICENSING AGREEMENT CeCILL\n\n- firstly, its conformity with French law, both as regards the law of torts and intellectual\nproperty law, and the protection that it offers to authors and the holders of economic rights\nover software.\n\n- secondly, compliance with the principles for the distribution of free software: access to source\ncodes, extended user-rights.\n\nCommissariat à l'Energie Atomique - CEA, a public scientific, technical and industrial\nestablishment, having its principal place of business at 31-33 rue de la Fédération, 75752\nPARIS cedex 15, France.\n\nCentre National de la Recherche Scientifique - CNRS, a public scientific and technological establishment,\nhaving its principal place of business at 3 rue Michel-Ange 75794 Paris cedex 16, France.\n\nInstitut National de Recherche en Informatique et en Automatique - INRIA, a public scientific and\ntechnological establishment, having its principal place of business at Domaine de Voluceau,\nRocquencourt, BP 105, 78153 Le Chesnay cedex.\n\nPREAMBLE\n\nThe purpose of this Free Software Licensing Agreement is to grant users the right to modify and\nredistribute the software governed by this license within the framework of an \"open source\"\ndistribution model.\n\nThe exercising of these rights is conditional upon certain obligations for users so as to ensure that\nthis status is retained for subsequent redistribution operations.\n\nAs a counterpart to the access to the source code and rights to copy, modify and redistribute granted by\nthe license, users are provided only with a limited warranty and the software's author, the\nholder of the economic rights, and the successive licensors only have limited liability.\n\nIn this respect, it is brought to the user's attention that the risks associated with loading,\nusing, modifying and/or developing or reproducing the software by the user given its nature of Free\nSoftware, that may mean that it is complicated to manipulate, and that also therefore means that it is\nreserved for developers and experienced professionals having in-depth computer knowledge. Users are\ntherefore encouraged to load and test the Software's suitability as regards their requirements in\nconditions enabling the security of their systems and/or data to be ensured and, more generally, to\nuse and operate it in the same conditions of security. This Agreement may be freely reproduced and\npublished, provided it is not altered, and that no Articles are either added or removed herefrom.\n\nThis Agreement may apply to any or all software for which the holder of the economic rights decides to\nsubmit the operation thereof to its provisions.\n\nArticle 1 - DEFINITIONS\n\nArticle 2 - PURPOSE\n\nArticle 3 - ACCEPTANCE\n\nArticle 4 - EFFECTIVE DATE AND TERM\n\nArticle 5 - SCOPE OF THE RIGHTS GRANTED\n\nArticle 6 - INTELLECTUAL PROPERTY\n\nArticle 7 - RELATED SERVICES\n\nArticle 8 - LIABILITY\n\nArticle 9 - WARRANTY\n\nArticle 10 - TERMINATION\n\nArticle 11 - MISCELLANEOUS PROVISIONS\n\nArticle 12 - NEW VERSIONS OF THE AGREEMENT\n\nArticle 13 - GOVERNING LAW AND JURISDICTION\n\nVersion 1.1 of 10/26/2004"
}